rabbitmq_worker/__init__.py
rabbitmq_worker/errors.py
rabbitmq_worker/producer.py
rabbitmq_worker/worker.py
rabbitmq_worker-0.0.7.dist-info/WHEEL
rabbitmq_worker-0.0.7.dist-info/METADATA
rabbitmq_worker-0.0.7.dist-info/RECORD
