Metadata-Version: 2.1
Name: rabbitmq_worker
Version: 0.0.7
Summary: Library to create simple rabbitmq workers resilient to connection/channel shutdown and simple producers.
Author-email: Enlaps Open Source <contact@enlaps.fr>
Requires-Python: >=3.8
Requires-Dist: pika>=1.2.0
Requires-Dist: pytest ; extra == "test"
Project-URL: Home, https://gitlab.com/enlaps/web/rabbitmq-worker
Provides-Extra: test
